drivebox
