Metadata-Version: 2.1
Name: drivebox
Version: 0.1.3
Summary: API for the Caonabo DribeBox (CDB)
Home-page: https://github.imec.be/dna-storage/drivebox
Author: César J. Lockhart de la Rosa
Author-email: lockhart@imec.be
License: MIT
Keywords: Switch Matriox,Potentiostat,Galvanostat,SMU,MUX,api,caonabo
Platform: UNKNOWN
Requires-Python: >=3
License-File: license.txt
